hawkei/__init__.py
hawkei/config.py
hawkei/constants.py
hawkei/message.py
hawkei/request.py
hawkei/store.py
hawkei/utils.py
hawkei/version.py
hawkei/plugins/django/middleware.py
hawkei/processor/__init__.py
hawkei/processor/asynchronous.py
hawkei/processor/batch.py
hawkei/processor/worker.py
hawkei/resources/batch.py
hawkei/resources/watcher.py
hawkei-1.1.0.dist-info/LICENCE
hawkei-1.1.0.dist-info/METADATA
hawkei-1.1.0.dist-info/WHEEL
hawkei-1.1.0.dist-info/top_level.txt
hawkei-1.1.0.dist-info/RECORD
