Metadata-Version: 2.1
Name: hawkei
Version: 1.1.0
Summary: Hawkei python integration
Home-page: https://github.com/hawkei-io/hawkei-python
Author: Hawkei
Author-email: support@hawkei.io
Maintainer: Hawkei
Maintainer-email: support@hawkei.io
License: MIT License
Platform: UNKNOWN
Classifier: License :: OSI Approved :: MIT License
Classifier: Programming Language :: Python
Classifier: Programming Language :: Python :: 3
Classifier: Programming Language :: Python :: 3.4
Classifier: Programming Language :: Python :: 3.5
Classifier: Programming Language :: Python :: 3.6
Classifier: Programming Language :: Python :: 3.7
Requires-Dist: requests (>=2)
Requires-Dist: backoff (>=1.8)
